README.rst
ediblepickle.py
setup.py
ediblepickle.egg-info/PKG-INFO
ediblepickle.egg-info/SOURCES.txt
ediblepickle.egg-info/dependency_links.txt
ediblepickle.egg-info/top_level.txt