Metadata-Version: 1.1
Name: ediblepickle
Version: 1.1.0
Summary: Checkpoint
Home-page: https://github.com/mpavan/ediblepickle
Author: Pavan Mallapragada
Author-email: UNKNOWN
License: Apache 2.0
Keywords: decorator,checkpoint,intermediate results,serialization,deserialization
Platform: UNKNOWN
Classifier: Intended Audience :: Developers
Classifier: Natural Language :: English
Classifier: License :: OSI Approved :: Apache Software License
Classifier: Programming Language :: Python
Classifier: Programming Language :: Python :: 2.6
Classifier: Programming Language :: Python :: 2.7
Classifier: Topic :: Utilities
